{
  "project_info": {
    "project_number": "161568734385",
    "project_id": "dailyquotes-01",
    "storage_bucket": "dailyquotes-01.appspot.com"
  },
  "client": [
    {
      "client_info": {
        "mobilesdk_app_id": "1:161568734385:android:60339fe3d4309560823690",
        "android_client_info": {
          "package_name": "com.techlyverse.quotes"
        }
      },
      "oauth_client": [
        {
          "client_id": "161568734385-gd050pei6k7uqv24qs5vtdfbge8ts3a8.apps.googleusercontent.com",
          "client_type": 3
        }
      ],
      "api_key": [
        {
          "current_key": "AIzaSyATz8PLm0ZWuc9ycy7cfU_wXaTdkWSBbX0"
        }
      ],
      "services": {
        "appinvite_service": {
          "other_platform_oauth_client": [
            {
              "client_id": "161568734385-gd050pei6k7uqv24qs5vtdfbge8ts3a8.apps.googleusercontent.com",
              "client_type": 3
            }
          ]
        }
      }
    }
  ],
  "configuration_version": "1"
}